{
	"format_version": "1.8.0",
	"animations": {
		"animation.butterfly.fly": {
			"loop": true,
			"animation_length": 0.2667,
			"bones": {
				"wingright": {
					"rotation": {
						"0.0": [0, 0, 40],
						"0.1333": [0, 0, -40],
						"0.2667": [0, 0, 40]
					}
				},
				"wingleft": {
					"rotation": {
						"0.0": [0, 0, -40],
						"0.1333": [0, 0, 40],
						"0.2667": [0, 0, -40]
					}
				},
				"right": {
					"rotation": {
						"0.0": [0, 0, 0],
						"0.1333": [0, 0, -17.5],
						"0.2667": [0, 0, 0]
					}
				},
				"left": {
					"rotation": {
						"0.0": [0, 0, 0],
						"0.1333": [0, 0, 17.5],
						"0.2667": [0, 0, 0]
					}
				}
			}
		}
	}
}