{
  "format_version": "1.12",
  "minecraft:recipe_shaped": {
    "description": {
    "identifier": "lostweapons:excalibur"
    },

    
    "tags": [ "crafting_table" ],
    "pattern": [
      "HAH",
      "HBH",
      "HCH"
    ],
    "key": {
      "H": {
        "item": "lostweapons:god_soul"
      },
      "A": {
        "item": "lostweapons:fragment_of_excalibur1"
      },
      "B": {
        "item": "lostweapons:fragment_of_excalibur2"
      },
      "C": {
        "item": "lostweapons:fragment_of_excalibur3"
      }
    },
    "result": [
      { "item": "lostweapons:excalibur" }
    ]
  }
}
